{
  "symbol": "THH",
  "type": "stock",
  "current_price": 34.479,
  "volume_24h": 948466,
  "change_24h": 0.0,
  "high_24h": 54.775,
  "low_24h": 12.27,
  "market_cap": 0,
  "pe_ratio": 0,
  "dividend_yield": 0,
  "historical_data": [
    {
      "timestamp": "2025-08-27T08:30:00",
      "price": 24.190000534057617,
      "volume": 88000
    },
    {
      "timestamp": "2025-08-28T08:30:00",
      "price": 6.019999980926514,
      "volume": 2611500
    },
    {
      "timestamp": "2025-08-29T08:30:00",
      "price": 5.429999828338623,
      "volume": 249200
    },
    {
      "timestamp": "2025-09-02T08:30:00",
      "price": 4.659999847412109,
      "volume": 165400
    },
    {
      "timestamp": "2025-09-03T08:30:00",
      "price": 4.800000190734863,
      "volume": 522300
    },
    {
      "timestamp": "2025-09-04T08:30:00",
      "price": 4.550000190734863,
      "volume": 143200
    },
    {
      "timestamp": "2025-09-05T08:30:00",
      "price": 4.949999809265137,
      "volume": 166600
    },
    {
      "timestamp": "2025-09-08T08:30:00",
      "price": 4.989999771118164,
      "volume": 75700
    },
    {
      "timestamp": "2025-09-09T08:30:00",
      "price": 5.699999809265137,
      "volume": 56900
    },
    {
      "timestamp": "2025-09-10T08:30:00",
      "price": 5.699999809265137,
      "volume": 86600
    },
    {
      "timestamp": "2025-09-11T08:30:00",
      "price": 6.099999904632568,
      "volume": 42000
    },
    {
      "timestamp": "2025-09-12T08:30:00",
      "price": 6.630000114440918,
      "volume": 55500
    },
    {
      "timestamp": "2025-09-15T08:30:00",
      "price": 7.050000190734863,
      "volume": 43500
    },
    {
      "timestamp": "2025-09-16T08:30:00",
      "price": 7.179999828338623,
      "volume": 24000
    },
    {
      "timestamp": "2025-09-17T08:30:00",
      "price": 8.270000457763672,
      "volume": 40900
    },
    {
      "timestamp": "2025-09-18T08:30:00",
      "price": 6.53000020980835,
      "volume": 82100
    },
    {
      "timestamp": "2025-09-19T08:30:00",
      "price": 6.869999885559082,
      "volume": 107300
    },
    {
      "timestamp": "2025-09-22T08:30:00",
      "price": 7.690000057220459,
      "volume": 94700
    },
    {
      "timestamp": "2025-09-23T08:30:00",
      "price": 7.010000228881836,
      "volume": 336400
    },
    {
      "timestamp": "2025-09-24T08:30:00",
      "price": 7.840000152587891,
      "volume": 51600
    },
    {
      "timestamp": "2025-09-25T08:30:00",
      "price": 8.010000228881836,
      "volume": 47700
    },
    {
      "timestamp": "2025-09-26T08:30:00",
      "price": 7.28000020980835,
      "volume": 50600
    },
    {
      "timestamp": "2025-09-29T08:30:00",
      "price": 7.059999942779541,
      "volume": 30900
    },
    {
      "timestamp": "2025-09-30T08:30:00",
      "price": 7.150000095367432,
      "volume": 97600
    },
    {
      "timestamp": "2025-10-01T08:30:00",
      "price": 6.010000228881836,
      "volume": 136500
    },
    {
      "timestamp": "2025-10-02T08:30:00",
      "price": 6.039999961853027,
      "volume": 37500
    },
    {
      "timestamp": "2025-10-03T08:30:00",
      "price": 6.25,
      "volume": 18200
    },
    {
      "timestamp": "2025-10-06T08:30:00",
      "price": 6.349999904632568,
      "volume": 14400
    },
    {
      "timestamp": "2025-10-07T08:30:00",
      "price": 7.420000076293945,
      "volume": 1893700
    },
    {
      "timestamp": "2025-10-08T08:30:00",
      "price": 7.820000171661377,
      "volume": 1535400
    },
    {
      "timestamp": "2025-10-09T08:30:00",
      "price": 7.199999809265137,
      "volume": 712100
    },
    {
      "timestamp": "2025-10-10T08:30:00",
      "price": 7.510000228881836,
      "volume": 1097000
    },
    {
      "timestamp": "2025-10-13T08:30:00",
      "price": 7.860000133514404,
      "volume": 1683300
    },
    {
      "timestamp": "2025-10-14T08:30:00",
      "price": 7.889999866485596,
      "volume": 852100
    },
    {
      "timestamp": "2025-10-15T08:30:00",
      "price": 8.170000076293945,
      "volume": 1938500
    },
    {
      "timestamp": "2025-10-16T08:30:00",
      "price": 7.710000038146973,
      "volume": 1702200
    },
    {
      "timestamp": "2025-10-17T08:30:00",
      "price": 7.710000038146973,
      "volume": 2201800
    },
    {
      "timestamp": "2025-10-20T08:30:00",
      "price": 8.220000267028809,
      "volume": 553100
    },
    {
      "timestamp": "2025-10-21T08:30:00",
      "price": 8.420000076293945,
      "volume": 1274700
    },
    {
      "timestamp": "2025-10-22T08:30:00",
      "price": 7.699999809265137,
      "volume": 675600
    },
    {
      "timestamp": "2025-10-23T08:30:00",
      "price": 8.3100004196167,
      "volume": 121700
    },
    {
      "timestamp": "2025-10-24T08:30:00",
      "price": 7.900000095367432,
      "volume": 45000
    },
    {
      "timestamp": "2025-10-27T08:30:00",
      "price": 8.899999618530273,
      "volume": 141300
    },
    {
      "timestamp": "2025-10-28T08:30:00",
      "price": 9.220000267028809,
      "volume": 79400
    },
    {
      "timestamp": "2025-10-29T08:30:00",
      "price": 8.819999694824219,
      "volume": 65200
    },
    {
      "timestamp": "2025-10-30T08:30:00",
      "price": 9.0600004196167,
      "volume": 85500
    },
    {
      "timestamp": "2025-10-31T08:30:00",
      "price": 8.65999984741211,
      "volume": 32100
    },
    {
      "timestamp": "2025-11-03T09:30:00",
      "price": 8.3100004196167,
      "volume": 156500
    },
    {
      "timestamp": "2025-11-04T09:30:00",
      "price": 8.619999885559082,
      "volume": 63800
    },
    {
      "timestamp": "2025-11-05T09:30:00",
      "price": 8.800000190734863,
      "volume": 31200
    },
    {
      "timestamp": "2025-11-06T09:30:00",
      "price": 8.34000015258789,
      "volume": 23000
    },
    {
      "timestamp": "2025-11-07T09:30:00",
      "price": 8.149999618530273,
      "volume": 51800
    },
    {
      "timestamp": "2025-11-10T09:30:00",
      "price": 8.720000267028809,
      "volume": 33000
    },
    {
      "timestamp": "2025-11-11T09:30:00",
      "price": 8.09000015258789,
      "volume": 92300
    },
    {
      "timestamp": "2025-11-12T09:30:00",
      "price": 8.100000381469727,
      "volume": 21100
    },
    {
      "timestamp": "2025-11-13T09:30:00",
      "price": 8.289999961853027,
      "volume": 45500
    },
    {
      "timestamp": "2025-11-14T09:30:00",
      "price": 8.369999885559082,
      "volume": 10400
    },
    {
      "timestamp": "2025-11-17T09:30:00",
      "price": 8.600000381469727,
      "volume": 69900
    },
    {
      "timestamp": "2025-11-18T09:30:00",
      "price": 8.399999618530273,
      "volume": 57900
    },
    {
      "timestamp": "2025-11-19T09:30:00",
      "price": 8.449999809265137,
      "volume": 17200
    },
    {
      "timestamp": "2025-11-20T09:30:00",
      "price": 8.069999694824219,
      "volume": 30400
    },
    {
      "timestamp": "2025-11-21T09:30:00",
      "price": 8.520000457763672,
      "volume": 28900
    },
    {
      "timestamp": "2025-11-24T09:30:00",
      "price": 9.300000190734863,
      "volume": 33000
    },
    {
      "timestamp": "2025-11-25T09:30:00",
      "price": 10.449999809265137,
      "volume": 45200
    },
    {
      "timestamp": "2025-11-26T09:30:00",
      "price": 12.5,
      "volume": 30800
    },
    {
      "timestamp": "2025-11-28T09:30:00",
      "price": 13.779999732971191,
      "volume": 25400
    },
    {
      "timestamp": "2025-12-01T09:30:00",
      "price": 14.979999542236328,
      "volume": 28200
    },
    {
      "timestamp": "2025-12-02T09:30:00",
      "price": 22.420000076293945,
      "volume": 234700
    },
    {
      "timestamp": "2025-12-03T09:30:00",
      "price": 16.600000381469727,
      "volume": 114700
    },
    {
      "timestamp": "2025-12-04T09:30:00",
      "price": 18.350000381469727,
      "volume": 43100
    },
    {
      "timestamp": "2025-12-05T09:30:00",
      "price": 18.5,
      "volume": 43200
    },
    {
      "timestamp": "2025-12-08T09:30:00",
      "price": 16.6299991607666,
      "volume": 59200
    },
    {
      "timestamp": "2025-12-09T09:30:00",
      "price": 13.020000457763672,
      "volume": 88400
    },
    {
      "timestamp": "2025-12-10T09:30:00",
      "price": 11.130000114440918,
      "volume": 75800
    },
    {
      "timestamp": "2025-12-11T09:30:00",
      "price": 9.84000015258789,
      "volume": 52800
    },
    {
      "timestamp": "2025-12-12T09:30:00",
      "price": 15.520000457763672,
      "volume": 476900
    },
    {
      "timestamp": "2025-12-15T09:30:00",
      "price": 12.579999923706055,
      "volume": 66000
    },
    {
      "timestamp": "2025-12-16T09:30:00",
      "price": 12.329999923706055,
      "volume": 7900
    },
    {
      "timestamp": "2025-12-17T09:30:00",
      "price": 12.779999732971191,
      "volume": 38600
    },
    {
      "timestamp": "2025-12-18T09:30:00",
      "price": 14.6899995803833,
      "volume": 315600
    },
    {
      "timestamp": "2025-12-19T09:30:00",
      "price": 15.390000343322754,
      "volume": 218500
    },
    {
      "timestamp": "2025-12-22T09:30:00",
      "price": 19.469999313354492,
      "volume": 158100
    },
    {
      "timestamp": "2025-12-23T09:30:00",
      "price": 17.895999908447266,
      "volume": 155400
    },
    {
      "timestamp": "2025-12-24T09:30:00",
      "price": 16.924999237060547,
      "volume": 205100
    },
    {
      "timestamp": "2025-12-26T09:30:00",
      "price": 16.934999465942383,
      "volume": 97600
    },
    {
      "timestamp": "2025-12-29T09:30:00",
      "price": 22.389999389648438,
      "volume": 535800
    },
    {
      "timestamp": "2025-12-30T09:30:00",
      "price": 18.950000762939453,
      "volume": 181400
    },
    {
      "timestamp": "2025-12-31T09:30:00",
      "price": 18.43000030517578,
      "volume": 99300
    },
    {
      "timestamp": "2026-01-02T09:30:00",
      "price": 20.364999771118164,
      "volume": 87600
    },
    {
      "timestamp": "2026-01-05T09:30:00",
      "price": 22.079999923706055,
      "volume": 110000
    },
    {
      "timestamp": "2026-01-06T09:30:00",
      "price": 19.170000076293945,
      "volume": 125300
    },
    {
      "timestamp": "2026-01-07T09:30:00",
      "price": 19.43000030517578,
      "volume": 97800
    },
    {
      "timestamp": "2026-01-08T09:30:00",
      "price": 21.6200008392334,
      "volume": 82000
    },
    {
      "timestamp": "2026-01-09T09:30:00",
      "price": 29.469999313354492,
      "volume": 202200
    },
    {
      "timestamp": "2026-01-12T09:30:00",
      "price": 23.100000381469727,
      "volume": 183400
    },
    {
      "timestamp": "2026-01-13T09:30:00",
      "price": 55.04999923706055,
      "volume": 490500
    },
    {
      "timestamp": "2026-01-14T15:05:42",
      "price": 34.47880172729492,
      "volume": 948466
    }
  ],
  "monthly_data": [
    {
      "timestamp": "2025-12-15T09:30:00",
      "price": 12.579999923706055,
      "volume": 66000
    },
    {
      "timestamp": "2025-12-16T09:30:00",
      "price": 12.329999923706055,
      "volume": 7900
    },
    {
      "timestamp": "2025-12-17T09:30:00",
      "price": 12.779999732971191,
      "volume": 38600
    },
    {
      "timestamp": "2025-12-18T09:30:00",
      "price": 14.6899995803833,
      "volume": 315600
    },
    {
      "timestamp": "2025-12-19T09:30:00",
      "price": 15.390000343322754,
      "volume": 218500
    },
    {
      "timestamp": "2025-12-22T09:30:00",
      "price": 19.469999313354492,
      "volume": 158100
    },
    {
      "timestamp": "2025-12-23T09:30:00",
      "price": 17.895999908447266,
      "volume": 155400
    },
    {
      "timestamp": "2025-12-24T09:30:00",
      "price": 16.924999237060547,
      "volume": 205100
    },
    {
      "timestamp": "2025-12-26T09:30:00",
      "price": 16.934999465942383,
      "volume": 97600
    },
    {
      "timestamp": "2025-12-29T09:30:00",
      "price": 22.389999389648438,
      "volume": 535800
    },
    {
      "timestamp": "2025-12-30T09:30:00",
      "price": 18.950000762939453,
      "volume": 181400
    },
    {
      "timestamp": "2025-12-31T09:30:00",
      "price": 18.43000030517578,
      "volume": 99300
    },
    {
      "timestamp": "2026-01-02T09:30:00",
      "price": 20.364999771118164,
      "volume": 87600
    },
    {
      "timestamp": "2026-01-05T09:30:00",
      "price": 22.079999923706055,
      "volume": 110000
    },
    {
      "timestamp": "2026-01-06T09:30:00",
      "price": 19.170000076293945,
      "volume": 125300
    },
    {
      "timestamp": "2026-01-07T09:30:00",
      "price": 19.43000030517578,
      "volume": 97800
    },
    {
      "timestamp": "2026-01-08T09:30:00",
      "price": 21.6200008392334,
      "volume": 82000
    },
    {
      "timestamp": "2026-01-09T09:30:00",
      "price": 29.469999313354492,
      "volume": 202200
    },
    {
      "timestamp": "2026-01-12T09:30:00",
      "price": 23.100000381469727,
      "volume": 183400
    },
    {
      "timestamp": "2026-01-13T09:30:00",
      "price": 55.04999923706055,
      "volume": 490500
    },
    {
      "timestamp": "2026-01-14T15:05:42",
      "price": 34.47880172729492,
      "volume": 948466
    }
  ],
  "indicators": {
    "rsi_14": 59.62469064077931,
    "rsi_30": 57.643520099722515,
    "sma_20": 21.547489976882936,
    "sma_50": 15.447596015930175,
    "bb_upper": 39.937024682489465,
    "bb_lower": 3.157955271276407,
    "bb_width": 1.706884163801501,
    "macd": 5.5635460533337024,
    "macd_signal": 5.5635460533337024,
    "macd_histogram": 0.0,
    "volatility_30d": 0.16778383796617807,
    "year_high": 55.04999923706055,
    "year_low": 4.550000190734863,
    "year_range": 50.499999046325684,
    "current_position": 0.5926495465694002,
    "invalidation_level": 29.307,
    "atr": 6.153371,
    "momentum_3m": 590.9579821397242,
    "volume_trend": "BULLISH_CONFIRMED"
  },
  "monthly_indicators": {
    "rsi_14": 59.62469064077931,
    "sma_20": 21.547489976882936,
    "bb_upper": 39.937024682489465,
    "bb_lower": 3.157955271276407,
    "bb_width": 1.706884163801501,
    "volatility_10d": 0.15171664653591674,
    "month_high": 55.04999923706055,
    "month_low": 12.329999923706055,
    "month_range": 42.71999931335449,
    "current_month_position": 0.5184644700278597,
    "momentum_1w": 79.85811992735559,
    "volume_trend": "BULLISH_CONFIRMED",
    "atr": 6.153371
  },
  "timestamp": "2026-01-14T15:06:35.142106",
  "source": "Yahoo Finance API"
}